{"churafont++ 32x14":{"charSpacing":"1"," ":{"ascent":"32","glyph":[".....",".....",".....",".....",".....",".....",".....",".....",".....",".....",".....",".....",".....",".....",".....",".....",".....",".....",".....",".....",".....",".....",".....",".....",".....",".....",".....",".....",".....",".....",".....",".....","....."]},"?":{"ascent":"32","glyph":[".",".",".",".",".",".",".",".",".",".",".",".",".",".",".",".",".",".",".",".",".",".",".",".",".",".",".",".",".",".",".",".","."]},"~":{"ascent":"32","glyph":["","","","","","","","","","","","","","","","","","","","","","","","","","","","","","","","",""]},"A":{"ascent":"32","glyph":["................","................","................","................","................","................","......###.......","......###.......",".....#####......",".....#####......",".....#####......","....###.###.....","....###.###.....","....###.###.....","...###...###....","...###...###....","...###...###....","..###.....###...","..###.....###...","..###.....###...",".#############..",".#############..",".###.......###..","###.........###.","###.........###.","###.........###.","................","................","................","................","................","................","................"]},"B":{"ascent":"32","glyph":["...............","...............","...............","...............","...............","...............","#########......","###########....","###.....####...","###......###...","###.......###..","###.......###..","###.......###..","###......###...","###.....####...","###########....","############...","###......####..","###.......###..","###........###.","###........###.","###........###.","###.......###..","###......####..","############...","##########.....","...............","...............","...............","...............","...............","...............","..............."]},"C":{"ascent":"32","glyph":["...............","...............","...............","...............","...............","...............",".....#####.....","...#########...","..####...####..","..###.....###..",".###.......###.",".###.......###.","###............","###............","###............","###............","###............","###............","###............","###............",".###.......###.",".###.......###.","..###.....###..","..####...####..","...#########...",".....#####.....","...............","...............","...............","...............","...............","...............","..............."]},"D":{"ascent":"32","glyph":["...............","...............","...............","...............","...............","...............","#########......","###########....","###.....####...","###......###...","###.......###..","###.......###..","###........###.","###........###.","###........###.","###........###.","###........###.","###........###.","###........###.","###........###.","###.......###..","###.......###..","###......###...","###.....####...","###########....","#########......","...............","...............","...............","...............","...............","...............","..............."]},"E":{"ascent":"32","glyph":["..............","..............","..............","..............","..............","..............","#############.","#############.","###...........","###...........","###...........","###...........","###...........","###...........","###...........","############..","############..","###...........","###...........","###...........","###...........","###...........","###...........","###...........","#############.","#############.","..............","..............","..............","..............","..............","..............",".............."]},"F":{"ascent":"32","glyph":["..............","..............","..............","..............","..............","..............","#############.","#############.","###...........","###...........","###...........","###...........","###...........","###...........","###...........","############..","############..","###...........","###...........","###...........","###...........","###...........","###...........","###...........","###...........","###...........","..............","..............","..............","..............","..............","..............",".............."]},"G":{"ascent":"32","glyph":["................","................","................","................","................","................",".....######.....","...##########...","..####....####..","..###......###..",".###........###.",".###........###.","###.............","###.............","###.............","###....########.","###....########.","###.........###.","###.........###.","###.........###.",".###.......####.",".###.......####.","..###.....#####.","..####...######.","...########.###.",".....#####..###.","................","................","................","................","................","................","................"]},"H":{"ascent":"32","glyph":["...............","...............","...............","...............","...............","...............","###........###.","###........###.","###........###.","###........###.","###........###.","###........###.","###........###.","###........###.","###........###.","##############.","##############.","###........###.","###........###.","###........###.","###........###.","###........###.","###........###.","###........###.","###........###.","###........###.","...............","...............","...............","...............","...............","...............","..............."]},"I":{"ascent":"32","glyph":["....","....","....","....","....","....","###.","###.","###.","###.","###.","###.","###.","###.","###.","###.","###.","###.","###.","###.","###.","###.","###.","###.","###.","###.","....","....","....","....","....","....","...."]},"J":{"ascent":"32","glyph":["..............","..............","..............","..............","..............","..............","..........###.","..........###.","..........###.","..........###.","..........###.","..........###.","..........###.","..........###.","..........###.","..........###.","..........###.","..........###.","..........###.","###.......###.","###.......###.","###.......###.",".###.....###..",".####...####..","..#########...","....#####.....","..............","..............","..............","..............","..............","..............",".............."]},"K":{"ascent":"32","glyph":["...............","...............","...............","...............","...............","...............","###.......####.","###......####..","###.....####...","###....####....","###...####.....","###..####......","###.####.......","#######........","######.........","#####..........","#####..........","######.........","#######........","###.####.......","###..####......","###...####.....","###....####....","###.....####...","###......####..","###.......####.","...............","...............","...............","...............","...............","...............","..............."]},"L":{"ascent":"32","glyph":["..............","..............","..............","..............","..............","..............","###...........","###...........","###...........","###...........","###...........","###...........","###...........","###...........","###...........","###...........","###...........","###...........","###...........","###...........","###...........","###...........","###...........","###...........","#############.","#############.","..............","..............","..............","..............","..............","..............",".............."]},"M":{"ascent":"32","glyph":["................","................","................","................","................","................","###.........###.","####.......####.","####.......####.","####.......####.","#####.....#####.","#####.....#####.","#####.....#####.","######...######.","######...######.","######...######.","###.###.###.###.","###.###.###.###.","###.###.###.###.","###..#####..###.","###..#####..###.","###..#####..###.","###...###...###.","###...###...###.","###...###...###.","###.........###.","................","................","................","................","................","................","................"]},"N":{"ascent":"32","glyph":["...............","...............","...............","...............","...............","...............","###........###.","####.......###.","####.......###.","#####......###.","#####......###.","######.....###.","#######....###.","###.###....###.","###.####...###.","###..####..###.","###..####..###.","###...####.###.","###....###.###.","###....#######.","###.....######.","###......#####.","###......#####.","###.......####.","###.......####.","###........###.","...............","...............","...............","...............","...............","...............","..............."]},"O":{"ascent":"32","glyph":["................","................","................","................","................","................",".....#####......","...#########....","..####...####...","..###.....###...",".###.......###..",".###.......###..","###.........###.","###.........###.","###.........###.","###.........###.","###.........###.","###.........###.","###.........###.","###.........###.",".###.......###..",".###.......###..","..###.....###...","..####...####...","...#########....",".....#####......","................","................","................","................","................","................","................"]},"P":{"ascent":"32","glyph":["...............","...............","...............","...............","...............","...............","##########.....","############...","###......####..","###.......###..","###.......####.","###........###.","###........###.","###........###.","###.......####.","###.......###..","###......####..","############...","##########.....","###............","###............","###............","###............","###............","###............","###............","...............","...............","...............","...............","...............","...............","..............."]},"Q":{"ascent":"32","glyph":["................","................","................","................","................","................",".....#####......","...#########....","..####...####...","..###.....###...",".###.......###..",".###.......###..","###.........###.","###.........###.","###.........###.","###.........###.","###.........###.","###.........###.","###.........###.","###.........###.",".###....###.###.",".###....######..","..###....####...","..####...#####..","...############.",".....######.###.","................","................","................","................","................","................","................"]},"R":{"ascent":"32","glyph":["...............","...............","...............","...............","...............","...............","##########.....","############...","###......####..","###.......###..","###.......####.","###........###.","###........###.","###.......####.","###.......###..","###......####..","############...","###########....","###.....####...","###......####..","###.......###..","###.......####.","###........###.","###........###.","###........###.","###........###.","...............","...............","...............","...............","...............","...............","..............."]},"S":{"ascent":"32","glyph":["...............","...............","...............","...............","...............","...............","....######.....","..##########...",".####....####..",".###......###..","###........###.","###........###.","####...........",".####..........","..######.......","....######.....","......######...",".........####..","..........####.","...........###.","###........###.","###........###.",".###......###..",".####....####..","..##########...","....######.....","...............","...............","...............","...............","...............","...............","..............."]},"T":{"ascent":"32","glyph":["..............","..............","..............","..............","..............","..............","#############.","#############.",".....###......",".....###......",".....###......",".....###......",".....###......",".....###......",".....###......",".....###......",".....###......",".....###......",".....###......",".....###......",".....###......",".....###......",".....###......",".....###......",".....###......",".....###......","..............","..............","..............","..............","..............","..............",".............."]},"U":{"ascent":"32","glyph":["...............","...............","...............","...............","...............","...............","###........###.","###........###.","###........###.","###........###.","###........###.","###........###.","###........###.","###........###.","###........###.","###........###.","###........###.","###........###.","###........###.","###........###.","###........###.","####......####.",".###......###..",".####....####..","..##########...","....######.....","...............","...............","...............","...............","...............","...............","..............."]},"V":{"ascent":"32","glyph":["................","................","................","................","................","................","###.........###.","###.........###.","###.........###.",".###.......###..",".###.......###..",".###.......###..","..###.....###...","..###.....###...","..###.....###...","...###...###....","...###...###....","...###...###....","....###.###.....","....###.###.....","....###.###.....",".....#####......",".....#####......",".....#####......","......###.......","......###.......","................","................","................","................","................","................","................"]},"W":{"ascent":"32","glyph":["..................","..................","..................","..................","..................","..................","###....###....###.","###....###....###.","###....###....###.","###....###....###.","###...#####...###.","###...#####...###.",".###..#####..###..",".###..#####..###..",".###..##.##..###..",".###.###.###.###..",".###.###.###.###..",".###.###.###.###..","..######.######...","..#####...#####...","..#####...#####...","..#####...#####...","..#####...#####...","..#####...#####...","...###.....###....","...###.....###....","..................","..................","..................","..................","..................","..................",".................."]},"X":{"ascent":"32","glyph":["...............","...............","...............","...............","...............","...............","###........###.","###........###.",".###......###..",".###......###..","..###....###...","..###....###...","...###..###....","...########....","....######.....",".....####......",".....####......","....######.....","...########....","...###..###....","..###....###...","..###....###...",".###......###..",".###......###..","###........###.","###........###.","...............","...............","...............","...............","...............","...............","..............."]},"Y":{"ascent":"32","glyph":["..............","..............","..............","..............","..............","..............","###.......###.","###.......###.",".###.....###..",".###.....###..",".###.....###..","..###...###...","..###...###...","..###...###...","...###.###....","...###.###....","....#####.....","....#####.....","....#####.....",".....###......",".....###......",".....###......",".....###......",".....###......",".....###......",".....###......","..............","..............","..............","..............","..............","..............",".............."]},"Z":{"ascent":"32","glyph":["...............","...............","...............","...............","...............","...............","##############.","##############.","..........####.","..........###..",".........####..","........####...","........###....",".......####....","......####.....","......###......",".....###.......","....####.......","...####........","...###.........","..####.........",".####..........",".###...........","####...........","##############.","##############.","...............","...............","...............","...............","...............","...............","..............."]},"0":{"ascent":"32","glyph":["...............","...............","...............","...............","...............","...............","....######.....","..##########...","..###....###...",".###......###..",".###......###..","###........###.","###........###.","###........###.","###........###.","###........###.","###........###.","###........###.","###........###.","###........###.","###........###.",".###......###..",".###......###..","..###....###...","..##########...","....######.....","...............","...............","...............","...............","...............","...............","..............."]},"1":{"ascent":"32","glyph":[".......",".......",".......",".......",".......",".......","...###.","...###.","...###.","######.","######.","...###.","...###.","...###.","...###.","...###.","...###.","...###.","...###.","...###.","...###.","...###.","...###.","...###.","...###.","...###.",".......",".......",".......",".......",".......",".......","......."]},"2":{"ascent":"32","glyph":["...............","...............","...............","...............","...............","...............","....######.....","..##########...",".####....####..",".###......###..","####......####.","###........###.","###........###.","###.......####.","..........###..",".........####..","........####...","......#####....","....######.....","...#####.......","..####.........",".####..........",".###...........","###............","##############.","##############.","...............","...............","...............","...............","...............","...............","..............."]},"3":{"ascent":"32","glyph":["...............","...............","...............","...............","...............","...............","....######.....","..##########...",".####....####..",".###......###..","###........###.","###........###.","...........###.","..........####.",".........####..",".....#######...",".....#######...",".........####..","..........####.","...........###.","###........###.","###........###.",".###......###..",".####....####..","..##########...","....######.....","...............","...............","...............","...............","...............","...............","..............."]},"4":{"ascent":"32","glyph":["...............","...............","...............","...............","...............","...............","........####...",".......#####...",".......#####...","......######...","......######...",".....#######...",".....###.###...","....####.###...","....###..###...","...####..###...","...###...###...","..####...###...","..###....###...",".####....###...",".###.....###...","##############.","##############.",".........###...",".........###...",".........###...","...............","...............","...............","...............","...............","...............","..............."]},"5":{"ascent":"32","glyph":["...............","...............","...............","...............","...............","...............","##############.","##############.","###............","###............","###............","###............","###............","###.######.....","############...","#####....####..","..........###..","..........####.","...........###.","...........###.","###........###.","####......####.",".###......###..",".####....####..","..##########...","....######.....","...............","...............","...............","...............","...............","...............","..............."]},"6":{"ascent":"32","glyph":["...............","...............","...............","...............","...............","...............","....######.....","..##########...",".####.....###..",".###.......##..","###............","###............","###.######.....","############...","#####....####..","####......###..","####......####.","###........###.","###........###.","###........###.","###........###.","####......####.",".###......###..",".####....####..","..##########...","....######.....","...............","...............","...............","...............","...............","...............","..............."]},"7":{"ascent":"32","glyph":["...............","...............","...............","...............","...............","...............","##############.","##############.","..........####.","..........###..",".........####..",".........###...","........####...","........###....",".......####....",".......###.....","......####.....","......###......",".....####......",".....###.......","....####.......","....###........","...####........","...###.........","..####.........","..###..........","...............","...............","...............","...............","...............","...............","..............."]},"8":{"ascent":"32","glyph":["...............","...............","...............","...............","...............","...............","....######.....","..##########...",".####....####..",".###......###..","###........###.","###........###.","####......####.",".####....####..","..##########...","..##########...",".####....####..","####......####.","###........###.","###........###.","###........###.","###........###.",".###......###..",".####....####..","..##########...","....######.....","...............","...............","...............","...............","...............","...............","..............."]},"9":{"ascent":"32","glyph":["...............","...............","...............","...............","...............","...............","....######.....","..##########...",".####....####..",".###......###..","####......####.","###........###.","###........###.","###........###.","###........###.","####......####.",".###......####.",".####....#####.","..############.","....######.###.","...........###.","...........###.",".##.......###..",".###.....####..","..##########...","....######.....","...............","...............","...............","...............","...............","...............","..............."]},"[":{"ascent":"32","glyph":[".......................",".......................",".......................",".......................",".......................","........######.........","......##########.......","....#####...######.....","...####........####....","..####....##.....###...","..###...#######..###...",".####...########.####..",".###.....############..","####.......###########.","#####..........#######.","#####............#####.","#######...........####.","#########.........####.","############......####.",".#############....###..",".####.########....###..","..###...######...###...","..###............###...","...####........####....","....######...#####.....","......##########.......","........######.........",".......................",".......................",".......................",".......................",".......................","......................."]},"]":{"ascent":"32","glyph":[".......................",".......................",".......................",".......................",".......................","######################.","######################.","####....######....####.","####....######....####.","####....######....####.","####....######....####.","####....######....####.","####....######....####.","####....######....####.","####....######....####.","####....######....####.","####....######....####.","####....######....####.","####....######....####.","####....######....####.","####....######....####.","#####....####....#####.","#####............#####.","######..........######.","########......########.","######################.","######################.",".......................",".......................",".......................",".......................",".......................","......................."]},"a":{"ascent":"32","glyph":["..............","..............","..............","..............","..............","..............","..............","..............","..............","..............","..............","..............","....######....","..##########..",".####....####.",".###......###.","..........###.",".........####.","...##########.",".########.###.","####......###.","###.......###.","###.......###.","####.....####.",".############.","...######.###.","..............","..............","..............","..............","..............","..............",".............."]},"b":{"ascent":"32","glyph":["...............","...............","...............","...............","...............","...............","###............","###............","###............","###............","###............","###............","###.######.....","############...","#####....####..","####......###..","###........###.","###........###.","###........###.","###........###.","###........###.","###........###.","####......###..","#####....####..","############...","###.######.....","...............","...............","...............","...............","...............","...............","..............."]},"c":{"ascent":"32","glyph":["..............","..............","..............","..............","..............","..............","..............","..............","..............","..............","..............","..............","....######....","..##########..",".####....###..",".###......###.","###.......###.","###...........","###...........","###...........","###...........","###.......###.",".###......###.",".####....###..","..##########..","....######....","..............","..............","..............","..............","..............","..............",".............."]},"d":{"ascent":"32","glyph":["...............","...............","...............","...............","...............","...............","...........###.","...........###.","...........###.","...........###.","...........###.","...........###.","....######.###.","..############.",".####....#####.",".###......####.","###........###.","###........###.","###........###.","###........###.","###........###.","###........###.",".###......####.",".####....#####.","..############.","....######.###.","...............","...............","...............","...............","...............","...............","..............."]},"e":{"ascent":"32","glyph":["...............","...............","...............","...............","...............","...............","...............","...............","...............","...............","...............","...............","....######.....","..##########...",".####....####..",".###......###..","###........###.","###........###.","##############.","##############.","###............","###............",".###......####.",".####....####..","..##########...","....######.....","...............","...............","...............","...............","...............","...............","..............."]},"f":{"ascent":"32","glyph":[".........",".........",".........",".........",".........",".........","....####.","...#####.","..####...","..###....","..###....","..###....","########.","########.","..###....","..###....","..###....","..###....","..###....","..###....","..###....","..###....","..###....","..###....","..###....","..###....",".........",".........",".........",".........",".........",".........","........."]},"g":{"ascent":"32","glyph":["...............","...............","...............","...............","...............","...............","...............","...............","...............","...............","...............","...............","....######.###.","..############.",".####....#####.",".###......####.","###........###.","###........###.","###........###.","###........###.","###........###.","###........###.",".###......####.",".####....#####.","..############.","....######.###.","...........###.",".###.......###.",".###......###..","..###....####..","..##########...","....######.....","..............."]},"h":{"ascent":"32","glyph":["..............","..............","..............","..............","..............","..............","###...........","###...........","###...........","###...........","###...........","###...........","###.######....","############..","####.....###..","###.......###.","###.......###.","###.......###.","###.......###.","###.......###.","###.......###.","###.......###.","###.......###.","###.......###.","###.......###.","###.......###.","..............","..............","..............","..............","..............","..............",".............."]},"i":{"ascent":"32","glyph":["....","....","....","....","....","....","###.","###.","###.","....","....","....","###.","###.","###.","###.","###.","###.","###.","###.","###.","###.","###.","###.","###.","###.","....","....","....","....","....","....","...."]},"j":{"ascent":"32","glyph":[".......",".......",".......",".......",".......",".......","...###.","...###.","...###.",".......",".......",".......","...###.","...###.","...###.","...###.","...###.","...###.","...###.","...###.","...###.","...###.","...###.","...###.","...###.","...###.","...###.","...###.","...###.","..###..","#####..","###....","......."]},"k":{"ascent":"32","glyph":[".............",".............",".............",".............",".............",".............","###..........","###..........","###..........","###..........","###..........","###..........","###.....####.","###....####..","###...####...","###..####....","###.####.....","#######......","######.......","######.......","#######......","###.####.....","###..####....","###...####...","###....####..","###.....####.",".............",".............",".............",".............",".............",".............","............."]},"l":{"ascent":"32","glyph":["....","....","....","....","....","....","###.","###.","###.","###.","###.","###.","###.","###.","###.","###.","###.","###.","###.","###.","###.","###.","###.","###.","###.","###.","....","....","....","....","....","....","...."]},"m":{"ascent":"32","glyph":["................","................","................","................","................","................","................","................","................","................","................","................","###.###...###...","########.#####..","####.#####.####.","###...###...###.","###...###...###.","###...###...###.","###...###...###.","###...###...###.","###...###...###.","###...###...###.","###...###...###.","###...###...###.","###...###...###.","###...###...###.","................","................","................","................","................","................","................"]},"n":{"ascent":"32","glyph":["..............","..............","..............","..............","..............","..............","..............","..............","..............","..............","..............","..............","###.######....","############..","####.....###..","###.......###.","###.......###.","###.......###.","###.......###.","###.......###.","###.......###.","###.......###.","###.......###.","###.......###.","###.......###.","###.......###.","..............","..............","..............","..............","..............","..............",".............."]},"o":{"ascent":"32","glyph":["...............","...............","...............","...............","...............","...............","...............","...............","...............","...............","...............","...............","....######.....","..##########...",".####....####..",".###......###..","###........###.","###........###.","###........###.","###........###.","###........###.","###........###.",".###......###..",".####....####..","..##########...","....######.....","...............","...............","...............","...............","...............","...............","..............."]},"p":{"ascent":"32","glyph":["...............","...............","...............","...............","...............","...............","...............","...............","...............","...............","...............","...............","###.######.....","############...","#####....####..","####......###..","###........###.","###........###.","###........###.","###........###.","###........###.","###........###.","####......###..","#####....####..","############...","###.######.....","###............","###............","###............","###............","###............","###............","..............."]},"q":{"ascent":"32","glyph":["...............","...............","...............","...............","...............","...............","...............","...............","...............","...............","...............","...............","....######.###.","..############.",".####....#####.",".###......####.","###........###.","###........###.","###........###.","###........###.","###........###.","###........###.",".###......####.",".####....#####.","..############.","....######.###.","...........###.","...........###.","...........###.","...........###.","...........###.","...........###.","..............."]},"r":{"ascent":"32","glyph":["............","............","............","............","............","............","............","............","............","............","............","............","###.######..","###########.","#####...###.","####........","####........","###.........","###.........","###.........","###.........","###.........","###.........","###.........","###.........","###.........","............","............","............","............","............","............","............"]},"s":{"ascent":"32","glyph":[".............",".............",".............",".............",".............",".............",".............",".............",".............",".............",".............",".............","...######....",".##########..","####....####.","###......###.","####.........",".#####.......","..######.....","....######...","......#####..","........####.","###......###.","####....####.",".##########..","...######....",".............",".............",".............",".............",".............",".............","............."]},"t":{"ascent":"32","glyph":["........","........","........","........","........","........","........","........","..###...","..###...","..###...","..###...","#######.","#######.","..###...","..###...","..###...","..###...","..###...","..###...","..###...","..###...","..###...","..###...","..#####.","...####.","........","........","........","........","........","........","........"]},"u":{"ascent":"32","glyph":["..............","..............","..............","..............","..............","..............","..............","..............","..............","..............","..............","..............","###.......###.","###.......###.","###.......###.","###.......###.","###.......###.","###.......###.","###.......###.","###.......###.","###.......###.","###.......###.","###.......###.",".###.....####.",".############.","...######.###.","..............","..............","..............","..............","..............","..............",".............."]},"v":{"ascent":"32","glyph":["..............","..............","..............","..............","..............","..............","..............","..............","..............","..............","..............","..............","###.......###.","###.......###.",".###.....###..",".###.....###..",".###.....###..","..###...###...","..###...###...","..###...###...","...###.###....","...###.###....","...###.###....","....#####.....","....#####.....",".....###......","..............","..............","..............","..............","..............","..............",".............."]},"w":{"ascent":"32","glyph":["................","................","................","................","................","................","................","................","................","................","................","................","###.........###.","###....#....###.","###...###...###.","###...###...###.","###...###...###.",".###..###..###..",".###.##.##.###..",".###.##.##.###..",".###.##.##.###..","..#####.#####...","..####...####...","..####...####...","..####...####...","...##.....##....","................","................","................","................","................","................","................"]},"x":{"ascent":"32","glyph":["..............","..............","..............","..............","..............","..............","..............","..............","..............","..............","..............","..............","####.....####.",".###.....###..",".####...####..","..###...###...","...###.###....","...#######....","....#####.....","....#####.....","...#######....","...###.###....","..###...###...",".####...####..",".###.....###..","####.....####.","..............","..............","..............","..............","..............","..............",".............."]},"y":{"ascent":"32","glyph":["..............","..............","..............","..............","..............","..............","..............","..............","..............","..............","..............","..............","###.......###.","###.......###.","###.......###.",".###.....###..",".###.....###..",".###.....###..","..###...###...","..###...###...","..###...###...","...###.###....","...###.###....","...###.###....","....#####.....","....#####.....","....#####.....",".....###......",".....###......","....####......",".######.......",".#####........",".............."]},"z":{"ascent":"32","glyph":[".............",".............",".............",".............",".............",".............",".............",".............",".............",".............",".............",".............","############.","############.","........####.",".......####..","......####...",".....####....",".....###.....","....###......","...####......","..####.......",".####........","####.........","############.","############.",".............",".............",".............",".............",".............",".............","............."]},"!":{"ascent":"32","glyph":["....","....","....","....","....","....","###.","###.","###.","###.","###.","###.","###.","###.","###.","###.","###.","###.","###.","###.","###.","....","....","###.","###.","###.","....","....","....","....","....","....","...."]},"'":{"ascent":"32","glyph":["...","...","...","...","...","...","##.","##.","##.","##.","...","...","...","...","...","...","...","...","...","...","...","...","...","...","...","...","...","...","...","...","...","...","..."]},"\"":{"ascent":"32","glyph":["......","......","......","......","......","......","##.##.","##.##.","##.##.","##.##.","......","......","......","......","......","......","......","......","......","......","......","......","......","......","......","......","......","......","......","......","......","......","......"]},"#":{"ascent":"32","glyph":["................","................","................","................","................","................","................","................","...###....###...","...###....###...","...###....###...","###############.","###############.","...###....###...","...###....###...","...###....###...","..###....###....","..###....###....","..###....###....","###############.","###############.","..###....###....","..###....###....","..###....###....","................","................","................","................","................","................","................","................","................"]},"(":{"ascent":"32","glyph":["......","......","......","......","......","..###.","..###.","..###.",".###..",".###..",".###..",".###..","###...","###...","###...","###...","###...","###...","###...","###...",".###..",".###..",".###..",".###..","..###.","..###.","..###.","......","......","......","......","......","......"]},")":{"ascent":"32","glyph":["......","......","......","......","......","###...","###...","###...",".###..",".###..",".###..",".###..","..###.","..###.","..###.","..###.","..###.","..###.","..###.","..###.",".###..",".###..",".###..",".###..","###...","###...","###...","......","......","......","......","......","......"]},"&":{"ascent":"32","glyph":["................","................","................","................","................","................","....####........","..########......","..###..###......",".###....###.....",".###....###.....",".###....###.....","..###..###......","..########......","...######.......","...#####........","..#######.......",".####.####......",".###...####.###.","###.....#######.","###.....######..","###......####...",".###....######..",".#############..","..########.####.","....####....###.","................","................","................","................","................","................","................"]},"+":{"ascent":"32","glyph":["..............","..............","..............","..............","..............","..............","..............","..............","..............","..............","..............","..............",".....###......",".....###......",".....###......",".....###......",".....###......","#############.","#############.",".....###......",".....###......",".....###......",".....###......",".....###......","..............","..............","..............","..............","..............","..............","..............","..............",".............."]},",":{"ascent":"32","glyph":["....","....","....","....","....","....","....","....","....","....","....","....","....","....","....","....","....","....","....","....","....","....","....","###.","###.","###.",".##.","##..","....","....","....","....","...."]},"-":{"ascent":"32","glyph":[".............",".............",".............",".............",".............",".............",".............",".............",".............",".............",".............",".............",".............",".............",".............",".............",".............","############.","############.",".............",".............",".............",".............",".............",".............",".............",".............",".............",".............",".............",".............",".............","............."]},".":{"ascent":"32","glyph":["....","....","....","....","....","....","....","....","....","....","....","....","....","....","....","....","....","....","....","....","....","....","....","###.","###.","###.","....","....","....","....","....","....","...."]},"\/":{"ascent":"32","glyph":[".............",".............",".............",".............",".............",".............",".........###.",".........###.","........###..","........###..",".......###...",".......###...","......###....","......###....",".....###.....",".....###.....","....###......","....###......","...###.......","...###.......","..###........","..###........",".###.........",".###.........","###..........","###..........",".............",".............",".............",".............",".............",".............","............."]},":":{"ascent":"32","glyph":["....","....","....","....","....","....","....","....","....","....","....","....","###.","###.","###.","....","....","....","....","....","....","###.","###.","###.","....","....","....","....","....","....","....","....","...."]},";":{"ascent":"32","glyph":["....","....","....","....","....","....","....","....","....","....","....","....","###.","###.","###.","....","....","....","....","....","....","###.","###.","###.",".##.","##..","....","....","....","....","....","....","...."]},"<":{"ascent":"32","glyph":["...........","...........","...........","...........","...........","...........","...........","...........","...........","...........","...........","...........","......####.",".....####..","....####...","...####....","..####.....",".####......","####.......","####.......",".####......","..####.....","...####....","....####...",".....####..","......####.","...........","...........","...........","...........","...........","...........","..........."]},"=":{"ascent":"32","glyph":[".............",".............",".............",".............",".............",".............",".............",".............",".............",".............",".............",".............",".............",".............","############.","############.",".............",".............",".............",".............","############.","############.",".............",".............",".............",".............",".............",".............",".............",".............",".............",".............","............."]},">":{"ascent":"32","glyph":["...........","...........","...........","...........","...........","...........","...........","...........","...........","...........","...........","...........","####.......",".####......","..####.....","...####....","....####...",".....####..","......####.","......####.",".....####..","....####...","...####....","..####.....",".####......","####.......","...........","...........","...........","...........","...........","...........","..........."]},"@":{"ascent":"32","glyph":[".................",".................",".................",".................",".................",".................","....########.....","..############...",".####......####..",".###........###..","###..........###.","###...###.##.###.","###..#######.###.","###.###..###.###.","###.##....##.###.","###.##....##.###.","###.##....##.###.","###.##....##.###.","###.###...##.###.","###..###########.","###...####.####..","###..............",".###........###..",".####......####..","..############...","....########.....",".................",".................",".................",".................",".................",".................","................."]},"{":{"ascent":"32","glyph":["...........................","...........................","...........................","...........................","...........................","...........................","##########################.","######....################.","####........#####..........","###....##....####..........","###...####...####..........","##...######...###..........","##...######...###..........","#...#############..........","#...#############..........","#...#####################..","#...#####################..","#...#############..........","#...#############..........","##...######...###..........","##...######...###..........","###...####...####..........","###....##....####..........","####........#####..........","######....################.","##########################.","...........................","...........................","...........................","...........................","...........................","...........................","..........................."]},"|":{"ascent":"32","glyph":["...........................","...........................","...........................","...........................","...........................","...........................","##########################.","#...#######...############.","#....######...###..........","#....######...###..........","#.....#####...###..........","#......####...###..........","#......####...###..........","#.......###...###..........","#...#...###...###..........","#...#....##...###########..","#...##....#...###########..","#...###...#...###..........","#...###.......###..........","#...####......###..........","#...####......###..........","#...#####.....###..........","#...######....###..........","#...######....###..........","#...#######...############.","##########################.","...........................","...........................","...........................","...........................","...........................","...........................","..........................."]},"}":{"ascent":"32","glyph":["............................","............................","............................","............................","............................","............................","######################......","#####.....##############....","###.........#####....####...","##....###....####.....###...","##...#####...####......###..","#...#######...###......###..","#...#######...###......###..","#....############.....###...","##.....##########....####...","####......##############....","######......#############...","########.....####.....####..","##########....###......###..","#...#######...###.......###.","#...#######...###.......###.","##...#####...####.......###.","##....###....####......###..","###.........#####.....####..","#####.....###############...","#######################.....","............................","............................","............................","............................","............................","............................","............................"]}}}